polyssifier/__init__.py
polyssifier/logger.py
polyssifier/poly_utils.py
polyssifier/polyssifier.py
polyssifier/report.py
polyssifier-1.0.15.dist-info/AUTHORS.md
polyssifier-1.0.15.dist-info/LICENSE
polyssifier-1.0.15.dist-info/METADATA
polyssifier-1.0.15.dist-info/WHEEL
polyssifier-1.0.15.dist-info/top_level.txt
polyssifier-1.0.15.dist-info/RECORD
